Metadata-Version: 2.1
Name: pylistmanagement
Version: 0.6
Summary: This library has 3 functions with which you can manage lists or columns of dataframes. You can impute, operate and filter.
Home-page: https://github.com/ikertxu123/pylistmanagement
Author: Beñat Basabe, Mario Rodriguez & Iker Nieto
Author-email: iker.nieto@alumni.mondragon.edu
License: MIT
Download-URL: https://github.com/ikertxu123/pylistmanagement/archive/refs/tags/v_06.tar.gz
Keywords: List,List Management,Filter,Impute
Platform: UNKNOWN
Classifier: Development Status :: 4 - Beta
Classifier: Intended Audience :: Developers
Classifier: Topic :: Software Development :: Build Tools
Classifier: License :: OSI Approved :: MIT License
Classifier: Programming Language :: Python :: 3
Classifier: Programming Language :: Python :: 3.4
Classifier: Programming Language :: Python :: 3.5
Classifier: Programming Language :: Python :: 3.6
Classifier: Programming Language :: Python :: 3.7
Classifier: Programming Language :: Python :: 3.8
Classifier: Programming Language :: Python :: 3.9
Classifier: Programming Language :: Python :: 3.10
License-File: LICENSE.txt
